wola_sdk/__init__.py
wola_sdk-0.0.3.dist-info/DESCRIPTION.rst
wola_sdk-0.0.3.dist-info/METADATA
wola_sdk-0.0.3.dist-info/RECORD
wola_sdk-0.0.3.dist-info/WHEEL
wola_sdk-0.0.3.dist-info/metadata.json
wola_sdk-0.0.3.dist-info/top_level.txt
