Metadata-Version: 2.0
Name: wola-sdk
Version: 0.0.3
Summary: Python SDK for Wola GraphQl
Home-page: https://github.com/mongkok/wola-sdk/
Author: Wola
Author-email: molina@waveapplication.com
License: UNKNOWN
Platform: UNKNOWN
Classifier: Development Status :: 1 - Planning
Classifier: Environment :: Web Environment
Classifier: Intended Audience :: Developers
Classifier: License :: OSI Approved :: MIT License
Classifier: Operating System :: OS Independent
Classifier: Programming Language :: Python
Classifier: Programming Language :: Python :: 3
Classifier: Programming Language :: Python :: 3.3
Classifier: Programming Language :: Python :: 3.4
Classifier: Programming Language :: Python :: 3.5
Classifier: Programming Language :: Python :: 3.6
Requires-Dist: gql (>=0.1.0)
